shared_dyamic_listing/__init__.py
shared_dyamic_listing/db.py
shared_dyamic_listing/models.py
shared_dyamic_listing/serializers.py
shared_dyamic_listing/services.py
shared_dynamic_listing-0.1.7.dist-info/LICENSE.txt
shared_dynamic_listing-0.1.7.dist-info/METADATA
shared_dynamic_listing-0.1.7.dist-info/WHEEL
shared_dynamic_listing-0.1.7.dist-info/top_level.txt
shared_dynamic_listing-0.1.7.dist-info/RECORD
